{
  "row_count": 500,
  "column_count": 22,
  "schema_valid": true,
  "missing_by_column": {
    "Borrower_ID": 0,
    "Age": 0,
    "Monthly_Income": 0,
    "Loan_Amount": 0,
    "Loan_Term_Months": 0,
    "Interest_Rate": 0,
    "Credit_Score": 0,
    "Days_Past_Due": 0,
    "Missed_Payments": 0,
    "Employment_Status": 0,
    "Loan_Purpose": 0,
    "Education_Level": 0,
    "Marital_Status": 0,
    "Num_Dependents": 0,
    "Residence_Type": 0,
    "Years_At_Current_Address": 0,
    "Outstanding_Balance": 0,
    "Collateral_Value": 0,
    "Debt_to_Income_Ratio": 0,
    "Collection_Attempts": 0,
    "Previous_Defaults": 0,
    "Recovery_Status": 0
  },
  "duplicate_rows": 0,
  "invalid_ranges": {
    "Age_outside_18_100": 0,
    "Interest_Rate_outside_0_100": 0,
    "Credit_Score_outside_300_900": 0,
    "Negative_financial_values": 0,
    "Negative_behavioral_values": 0,
    "Debt_to_Income_outside_0_3": 0,
    "Outstanding_exceeds_loan_amount": 180,
    "Recovery_Status_outside_0_2": 0
  },
  "iqr_outliers": {
    "Age": 0,
    "Monthly_Income": 0,
    "Loan_Amount": 0,
    "Loan_Term_Months": 0,
    "Interest_Rate": 0,
    "Credit_Score": 0,
    "Days_Past_Due": 0,
    "Missed_Payments": 0,
    "Num_Dependents": 0,
    "Years_At_Current_Address": 0,
    "Outstanding_Balance": 0,
    "Collateral_Value": 0,
    "Debt_to_Income_Ratio": 0,
    "Collection_Attempts": 0,
    "Previous_Defaults": 0
  },
  "blocking_issues": [],
  "warnings": [
    "180 loans have outstanding balance above original loan amount."
  ]
}